tests/__init__.py
tests/dbops/__init__.py
tests/dbops/mysql_op.py
tests/dispatch/__init__.py
tests/dispatch/config/__init__.py
tests/dispatch/config/celery_local_config.py
tests/dispatch/rules/__init__.py
tests/dispatch/rules/rule_temp.py
tests/dispatch/test_dispatch.py
tests/helpers/__init__.py
tests/helpers/test_mysql_helper.py
tests/helpers/test_pika_helper.py
tests/helpers/test_redis_helper.py
tests/submit/__init__.py
tests/submit/schedule_rule/__init__.py
tests/submit/schedule_rule/schedule/__init__.py
tests/submit/schedule_rule/schedule/statistic_task/__init__.py
tests/submit/schedule_rule/schedule/statistic_task/schedule_statistic_collect_test.py
tests/submit/schedule_rule/schedule/statistic_task/schedule_statistic_task_test.py
tests/submit/schedule_rule/schedule/work_flow/__init__.py
tests/submit/schedule_rule/schedule/work_flow/schedule_work_flow_test.py
tests/submit/submit.json
tests/submit/test_submit.py
tests/test_ip2region.py
tests/test_logger.py
tests/test_xtrace.py
tests/utils/__init__.py
tests/xcelery/__init__.py
tests/xcelery/config/__init__.py
tests/xcelery/config/celery_local_config.py
tests/xcelery/task_register.py
tests/xcelery/test_celery.py
yyxx_game_pkg/__init__.py
yyxx_game_pkg/center_api/__init__.py
yyxx_game_pkg/center_api/model/Operator.py
yyxx_game_pkg/center_api/model/OperatorServer.py
yyxx_game_pkg/center_api/model/RechargeConfig.py
yyxx_game_pkg/center_api/model/TableFieldConf.py
yyxx_game_pkg/center_api/model/__init__.py
yyxx_game_pkg/center_api/sdk/__init__.py
yyxx_game_pkg/center_api/sdk/check_token.py
yyxx_game_pkg/center_api/sdk/map_core.py
yyxx_game_pkg/center_api/sdk/recharge.py
yyxx_game_pkg/conf/__init__.py
yyxx_game_pkg/conf/global_settings.py
yyxx_game_pkg/crypto/__init__.py
yyxx_game_pkg/crypto/aes.py
yyxx_game_pkg/crypto/basic.py
yyxx_game_pkg/crypto/make_sign.py
yyxx_game_pkg/crypto/rsa.py
yyxx_game_pkg/dbops/__init__.py
yyxx_game_pkg/dbops/base.py
yyxx_game_pkg/dbops/ch_op.py
yyxx_game_pkg/dbops/das_api.py
yyxx_game_pkg_compat-2024.2.23.1.dist-info/METADATA
yyxx_game_pkg_compat-2024.2.23.1.dist-info/WHEEL
yyxx_game_pkg_compat-2024.2.23.1.dist-info/RECORD
