Metadata-Version: 2.1
Name: yyxx-game-pkg-compat
Version: 2024.2.23.1
Summary: yyxx game custom module on compat
Home-page: https://github.com/yyxxgame/yyxxgame-pkg
License: MIT
Author: yyxx-game
Requires-Python: >=3.6.0,<4.0.0
Classifier: License :: OSI Approved :: MIT License
Classifier: Operating System :: OS Independent
Classifier: Programming Language :: Python :: 3
Classifier: Programming Language :: Python :: 3.6
Classifier: Programming Language :: Python :: 3.7
Classifier: Programming Language :: Python :: 3.8
Classifier: Programming Language :: Python :: 3.9
Classifier: Programming Language :: Python :: 3.10
Classifier: Programming Language :: Python :: 3.11
Classifier: Programming Language :: Python :: 3.12
Requires-Dist: flask (>=2.0.3,<3.0.0)
Requires-Dist: line-profiler (>=4.0.3,<5.0.0)
Requires-Dist: opentelemetry-api (>=1.12.0,<2.0.0)
Requires-Dist: opentelemetry-exporter-jaeger (>=1.12.0,<2.0.0)
Requires-Dist: opentelemetry-instrumentation-celery (==0.33b0)
Requires-Dist: opentelemetry-instrumentation-django (>=0.33b0,<0.34)
Requires-Dist: opentelemetry-instrumentation-fastapi (==0.33b.0)
Requires-Dist: opentelemetry-instrumentation-flask (>=0.33b0,<0.34)
Requires-Dist: opentelemetry-instrumentation-pymysql (>=0.33b0,<0.34)
Requires-Dist: opentelemetry-instrumentation-redis (>=0.33b0,<0.34)
Requires-Dist: opentelemetry-instrumentation-requests (>=0.33b0,<0.34)
Requires-Dist: opentelemetry-sdk (>=1.12.0,<2.0.0)
Requires-Dist: toml (>=0.10.2,<0.11.0)
Project-URL: Repository, https://github.com/yyxxgame/yyxxgame-pkg
